Workbook
Name SegmentaciónDeDatos_Organización_compras: #N/A
Name SegmentaciónDeDatos_Tipo: #N/A

Sheet BB_DD
A1: Centro | B1: País | C1: Organización compras | D1: Grupo de compras | E1: G.compras | F1: Solicitante | G1: Tipo | H1: Solicitud de pedido | I1: Posición de pedido | J1: Pedido | K1: Texto breve | L1: Fecha de solicitud | M1: Creado por | N1: Clase documento | O1: Grupo de artículos | P1: Proveedor fijo | Q1: Nombre de proveedor | R1: Valor total | S1: Valor total USD | T1: Moneda | U1: Indicador de borrado
A2: BIN | B2: =LEFT(Tabla1[[#This Row],[Organización compras]],2) -> CL | C2: CL01 | D2: 634 | E2: =VLOOKUP(Tabla1[[#This Row],[Grupo de compras]],'Grupo compras'!$A$1:$B$115,2,FALSE) -> CL Proyectos 5 | F2: RSOUPER | G2: =LEFT(Tabla1[[#This Row],[Solicitud de pedido]],2) -> 13 | H2: 1300008890 | I2: 10 | J2: 5000008621 | K2: Construcción Outlet Buin | L2: 46056 | M2: EXT_AYEPEZ | N2: ZSPC | P2: 96869030 | Q2: CONSTRUCTORA CUEVAS Y PURCELL S.A. | R2: 325400 | S2: =Tabla1[[#This Row],[Valor total]]/'T.C.'!$B$4 -> 13558333 | T2: UF | U2: false
A3: AEB | B3: =LEFT(Tabla1[[#This Row],[Organización compras]],2) -> CL | C3: CL01 | D3: 634 | E3: =VLOOKUP(Tabla1[[#This Row],[Grupo de compras]],'Grupo compras'!$A$1:$B$115,2,FALSE) -> CL Proyectos 5 | F3: RSOUPER | G3: =LEFT(Tabla1[[#This Row],[Solicitud de pedido]],2) -> 13 | H3: 1300008897 | I3: 10 | J3: 5000008640 | K3: Reconversión Adidas | L3: 46065 | M3: EXT_AYEPEZ | N3: ZSPC | P3: 77058836 | Q3: LUNA NESVARA CONSTRUCTORA SPA | R3: 10231 | S3: =Tabla1[[#This Row],[Valor total]]/'T.C.'!$B$4 -> 426291.67 | T3: UF | U3: false
A4: 1100 | B4: =LEFT(Tabla1[[#This Row],[Organización compras]],2) -> CL | C4: CL01 | D4: 911 | E4: =VLOOKUP(Tabla1[[#This Row],[Grupo de compras]],'Grupo compras'!$A$1:$B$115,2,FALSE) -> Corp A. Finanzas | F4: atoloza | G4: =LEFT(Tabla1[[#This Row],[Solicitud de pedido]],2) -> 14 | H4: 1400009325 | I4: 10 | J4: 5400006839 | K4: Comisiones pendientes – Roles RTB y Banc | L4: 46084 | M4: PMUNOZ | N4: ZPMH | P4: 97036000 | Q4: BANCO SANTANDER CHILE | R4: 363745833 | S4: =Tabla1[[#This Row],[Valor total]]/'T.C.'!$B$3 -> 392843.77 | T4: CLP | U4: false
A5: MIN | B5: =LEFT(Tabla1[[#This Row],[Organización compras]],2) -> PE | C5: PE01 | D5: 802 | E5: =VLOOKUP(Tabla1[[#This Row],[Grupo de compras]],'Grupo compras'!$A$1:$B$115,2,FALSE) -> PE Ops Mall | F5: cpisfil | G5: =LEFT(Tabla1[[#This Row],[Solicitud de pedido]],2) -> 13 | H5: 1300008836 | I5: 10 | J5: 5000008576 | K5: SRV ADMINIST. DE ESTACI _2026 | L5: 46042 | M5: EXT_EDAVILA | N5: ZSPC | P5: P60338169 | Q5: INVERSIONES URBANISTICAS OPERADORA | R5: 1112964 | S5: =Tabla1[[#This Row],[Valor total]]/'T.C.'!$B$2 -> 322598.26 | T5: PEN | U5: false
A6: 1100 | B6: =LEFT(Tabla1[[#This Row],[Organización compras]],2) -> CL | C6: CL01 | D6: 635 | E6: =VLOOKUP(Tabla1[[#This Row],[Grupo de compras]],'Grupo compras'!$A$1:$B$115,2,FALSE) -> CL Proyectos 6 | F6: CGARCI | G6: =LEFT(Tabla1[[#This Row],[Solicitud de pedido]],2) -> 12 | H6: 1200144791 | I6: 10 | J6: 4900149406 | K6: HITO 3 etapa 2B | L6: 46051 | M6: EXT_AYEPEZ | N6: ZSRV | P6: 76451328 | Q6: MESA ARQUITECTURA LIMITADA | R6: 6513.2 | S6: =Tabla1[[#This Row],[Valor total]]/'T.C.'!$B$4 -> 271383.33 | T6: UF | U6: false
A7: 6000 | B7: =LEFT(Tabla1[[#This Row],[Organización compras]],2) -> PE | C7: PEMP | D7: 816 | E7: =VLOOKUP(Tabla1[[#This Row],[Grupo de compras]],'Grupo compras'!$A$1:$B$115,2,FALSE) -> PE Sgcia Infra | F7: MMURGUIA | G7: =LEFT(Tabla1[[#This Row],[Solicitud de pedido]],2) -> 13 | H7: 1300008879 | I7: 10 | J7: 5000008617 | K7: Mesas, sillas y tachos de basura - Distr | L7: 46055 | M7: EXT_ACHIHUAN | N7: ZSPC | P7: P51281489 | Q7: G. SEMPERTEGUI PROYECTOS GENERAL | R7: 556010.94 | S7: =Tabla1[[#This Row],[Valor total]]/'T.C.'!$B$2 -> 161162.59 | T7: PEN | U7: false
A8: 6000 | B8: =LEFT(Tabla1[[#This Row],[Organización compras]],2) -> PE | C8: PEMP | D8: 811 | E8: =VLOOKUP(Tabla1[[#This Row],[Grupo de compras]],'Grupo compras'!$A$1:$B$115,2,FALSE) -> PE Área Admin | F8: JRODRIGUEZS | G8: =LEFT(Tabla1[[#This Row],[Solicitud de pedido]],2) -> 12 | H8: 1200143922 | I8: 10 | J8: 4900148645 | K8: Lucro Cesante por perdida de venta gener | L8: 46034 | M8: GRAVINES | N8: ZSRV | O8: SER_GRAL | P8: P33756437 | Q8: TIENDAS POR DEPARTAMENTO RIPLEY S.A | R8: 531274 | S8: =Tabla1[[#This Row],[Valor total]]/'T.C.'!$B$2 -> 153992.46 | T8: PEN | U8: false
A9: 6000 | B9: =LEFT(Tabla1[[#This Row],[Organización compras]],2) -> PE | C9: PEMP | D9: 816 | E9: =VLOOKUP(Tabla1[[#This Row],[Grupo de compras]],'Grupo compras'!$A$1:$B$115,2,FALSE) -> PE Sgcia Infra | F9: MMURGUIA | G9: =LEFT(Tabla1[[#This Row],[Solicitud de pedido]],2) -> 13 | H9: 1300008891 | I9: 10 | J9: 5000008631 | K9: Supervisión MP Independencia Distrito Ga | L9: 46057 | M9: EXT_ACHIHUAN | N9: ZSPC | P9: P10228549 | Q9: SCHMIDT & CHAVEZ TAFUR INGENIEROS S | R9: 511117.48 | S9: =Tabla1[[#This Row],[Valor total]]/'T.C.'!$B$2 -> 148149.99 | T9: PEN | U9: false
A10: 1100 | B10: =LEFT(Tabla1[[#This Row],[Organización compras]],2) -> CL | C10: CL01 | D10: 914 | E10: =VLOOKUP(Tabla1[[#This Row],[Grupo de compras]],'Grupo compras'!$A$1:$B$115,2,FALSE) -> Corp Explo. TI | F10: CPAVEZ | G10: =LEFT(Tabla1[[#This Row],[Solicitud de pedido]],2) -> 12 | H10: 1200143992 | I10: 10 | J10: 4900148769 | K10: RENOVACION LICENCIAS ATLASSIAN | L10: 46036 | M10: CPAVEZ | N10: ZSRV | O10: SER_GRAL | P10: 76924900 | Q10: TSOFT CHILE SPA | R10: 142350 | S10: =Tabla1[[#This Row],[Valor total]] -> 142350 | T10: USD | U10: false
A11: MQU | B11: =LEFT(Tabla1[[#This Row],[Organización compras]],2) -> CL | C11: CL01 | D11: 602 | E11: =VLOOKUP(Tabla1[[#This Row],[Grupo de compras]],'Grupo compras'!$A$1:$B$115,2,FALSE) -> CL Ops Mall | F11: MBELLO | G11: =LEFT(Tabla1[[#This Row],[Solicitud de pedido]],2) -> 12 | H11: 1200144958 | I11: 10 | J11: 4900149553 | K11: Analiticas MAQ cctv etapa final | L11: 46056 | M11: EXT_MBELLO | N11: ZSRV | P11: 77350771 | Q11: 4EVER GROUP SPA | R11: 124249365 | S11: =Tabla1[[#This Row],[Valor total]]/'T.C.'!$B$3 -> 134188.72 | T11: CLP | U11: false
A12: 6740 | B12: =LEFT(Tabla1[[#This Row],[Organización compras]],2) -> PE | C12: PEMP | D12: 816 | E12: =VLOOKUP(Tabla1[[#This Row],[Grupo de compras]],'Grupo compras'!$A$1:$B$115,2,FALSE) -> PE Sgcia Infra | F12: MMURGUIA | H12: 1300008966 | I12: 10 | J12: 5000008689 | K12: Obra para Habilitación Urbana de Vía REA | L12: 46092 | M12: EXT_ACHIHUAN | N12: ZSPC | P12: P60285686 | Q12: GESVAL S.A.C | R12: 451000 | S12: =Tabla1[[#This Row],[Valor total]]/'T.C.'!$B$2 -> 130724.64 | T12: PEN | U12: false
A13: 6000 | B13: =LEFT(Tabla1[[#This Row],[Organización compras]],2) -> PE | C13: PEMP | D13: 811 | E13: =VLOOKUP(Tabla1[[#This Row],[Grupo de compras]],'Grupo compras'!$A$1:$B$115,2,FALSE) -> PE Área Admin | F13: JRODRIGUEZS | G13: =LEFT(Tabla1[[#This Row],[Solicitud de pedido]],2) -> 12 | H13: 1200146527 | I13: 10 | J13: 4900150865 | K13: Lucro Cesante por perdida de venta gener | L13: 46083 | M13: GRAVINES | N13: ZSRV | O13: SER_GRAL | P13: P33756437 | Q13: TIENDAS POR DEPARTAMENTO RIPLEY S.A | R13: 405165 | S13: =Tabla1[[#This Row],[Valor total]]/'T.C.'!$B$2 -> 117439.13 | T13: PEN | U13: false
A14: MIN | B14: =LEFT(Tabla1[[#This Row],[Organización compras]],2) -> PE | C14: PE01 | D14: 801 | E14: =VLOOKUP(Tabla1[[#This Row],[Grupo de compras]],'Grupo compras'!$A$1:$B$115,2,FALSE) -> PE Center Manager | F14: jbalcazar | G14: =LEFT(Tabla1[[#This Row],[Solicitud de pedido]],2) -> 13 | H14: 1300008843 | I14: 10 | J14: 5000008569 | K14: SRV PERSONAL SEG. ENE-DIC26 | L14: 46041 | M14: EXT_EDAVILA | N14: ZSPC | P14: P60307606 | Q14: SESEPOL PERU S.A.C. | R14: 398418 | S14: =Tabla1[[#This Row],[Valor total]]/'T.C.'!$B$2 -> 115483.48 | T14: PEN | U14: false
A15: 6000 | B15: =LEFT(Tabla1[[#This Row],[Organización compras]],2) -> PE | C15: PEMP | D15: 816 | E15: =VLOOKUP(Tabla1[[#This Row],[Grupo de compras]],'Grupo compras'!$A$1:$B$115,2,FALSE) -> PE Sgcia Infra | F15: AGALVAN | G15: =LEFT(Tabla1[[#This Row],[Solicitud de pedido]],2) -> 13 | H15: 1300008946 | I15: 10 | J15: 5000008670 | K15: PLAN DE MITIGACIÓN MPI | L15: 46085 | M15: EXT_ACHIHUAN | N15: ZSPC | O15: SER_GRAL | P15: P42465666 | Q15: EDIFICACIONES DEL SUR S.A.C. | R15: 393069.43 | S15: =Tabla1[[#This Row],[Valor total]]/'T.C.'!$B$2 -> 113933.17 | T15: PEN | U15: false
A16: 1100 | B16: =LEFT(Tabla1[[#This Row],[Organización compras]],2) -> CL | C16: CL01 | D16: 930 | E16: =VLOOKUP(Tabla1[[#This Row],[Grupo de compras]],'Grupo compras'!$A$1:$B$115,2,FALSE) -> Corp Desarro. TI | F16: CVERGARA | G16: =LEFT(Tabla1[[#This Row],[Solicitud de pedido]],2) -> 12 | H16: 1200146393 | I16: 10 | J16: 4900150608 | K16: HubSpot 2026 | L16: 46079 | M16: CVERGARA | N16: ZSRV | O16: SER_GRAL | P16: 20263279 | Q16: HUBSPOT, INC. | R16: 110996.82 | S16: =Tabla1[[#This Row],[Valor total]] -> 110996.82 | T16: USD | U16: false
A17: 2400 | B17: =LEFT(Tabla1[[#This Row],[Organización compras]],2) -> CL | C17: CL01 | D17: 602 | E17: =VLOOKUP(Tabla1[[#This Row],[Grupo de compras]],'Grupo compras'!$A$1:$B$115,2,FALSE) -> CL Ops Mall | F17: p.herrera | G17: =LEFT(Tabla1[[#This Row],[Solicitud de pedido]],2) -> 13 | H17: 1300008825 | I17: 10 | J17: 5000008556 | K17: Proyecto Paneles FV CAL | L17: 46029 | M17: EXT_PHERRERA | N17: ZSPC | P17: 76172285 | Q17: COPEC FLUX SPA | R17: 2557.5 | S17: =Tabla1[[#This Row],[Valor total]]/'T.C.'!$B$4 -> 106562.5 | T17: UF | U17: false
A18: 1100 | B18: =LEFT(Tabla1[[#This Row],[Organización compras]],2) -> CL | C18: CL01 | D18: 613 | E18: =VLOOKUP(Tabla1[[#This Row],[Grupo de compras]],'Grupo compras'!$A$1:$B$115,2,FALSE) -> CL Gcia Ops | F18: p.herrera | G18: =LEFT(Tabla1[[#This Row],[Solicitud de pedido]],2) -> 12 | H18: 1200144667 | I18: 10 | J18: 4900149369 | K18: ASESORIA MERCADO ELECTRICO 2026 | L18: 46049 | M18: EXT_PHERRERA | N18: ZSRV | O18: SER_GRAL | P18: 78585040 | Q18: ASESORIAS Y RENTAS ECLIPSE LTDA | R18: 2500 | S18: =Tabla1[[#This Row],[Valor total]]/'T.C.'!$B$4 -> 104166.67 | T18: UF | U18: false
A19: MIN | B19: =LEFT(Tabla1[[#This Row],[Organización compras]],2) -> PE | C19: PE01 | D19: 802 | E19: =VLOOKUP(Tabla1[[#This Row],[Grupo de compras]],'Grupo compras'!$A$1:$B$115,2,FALSE) -> PE Ops Mall | F19: CPISFIL | G19: =LEFT(Tabla1[[#This Row],[Solicitud de pedido]],2) -> 13 | H19: 1300008882 | I19: 10 | J19: 5000008624 | K19: LIMPIEZA DE TECHOS 2026 | L19: 46057 | M19: EXT_EDAVILA | N19: ZSPC | P19: P60170752 | Q19: GROUP ANMI BLASTER S.A.C. | R19: 333727.08 | S19: =Tabla1[[#This Row],[Valor total]]/'T.C.'!$B$2 -> 96732.487 | T19: PEN | U19: false
A20: MQU | B20: =LEFT(Tabla1[[#This Row],[Organización compras]],2) -> CL | C20: CL01 | D20: 634 | E20: =VLOOKUP(Tabla1[[#This Row],[Grupo de compras]],'Grupo compras'!$A$1:$B$115,2,FALSE) -> CL Proyectos 5 | F20: RMOYA | G20: =LEFT(Tabla1[[#This Row],[Solicitud de pedido]],2) -> 13 | H20: 1300008862 | I20: 10 | J20: 5000008593 | K20: Etapa 1 MasterMAQ | L20: 46048 | M20: EXT_AYEPEZ | N20: ZSPC | P20: 76054243 | Q20: G5 ARQUITECTOS S.A. | R20: 2293.58 | S20: =Tabla1[[#This Row],[Valor total]]/'T.C.'!$B$4 -> 95565.833 | T20: UF | U20: false
A21: 4300 | B21: =LEFT(Tabla1[[#This Row],[Organización compras]],2) -> CO | C21: CO01 | D21: 702 | E21: =VLOOKUP(Tabla1[[#This Row],[Grupo de compras]],'Grupo compras'!$A$1:$B$115,2,FALSE) -> CO Ops Mall | F21: ARICO | G21: =LEFT(Tabla1[[#This Row],[Solicitud de pedido]],2) -> 13 | H21: 1300008906 | I21: 10 | J21: 5000008650 | K21: CAPEX TTVV PAR F3 - 2026 | L21: 46072 | M21: EXT_JTRUJILL | N21: ZSPC | P21: C860005289 | Q21: ASCENSORES SCHINDLER DE COLOMBIA S. | R21: 341457665 | S21: =Tabla1[[#This Row],[Valor total]]/'T.C.'!$B$5 -> 92837.864 | T21: COP | U21: false
A22: 4300 | B22: =LEFT(Tabla1[[#This Row],[Organización compras]],2) -> CO | C22: CO01 | D22: 719 | E22: =VLOOKUP(Tabla1[[#This Row],[Grupo de compras]],'Grupo compras'!$A$1:$B$115,2,FALSE) -> CO Gcia Ing | F22: JVASQUEZ | G22: =LEFT(Tabla1[[#This Row],[Solicitud de pedido]],2) -> 13 | H22: 1300008961 | I22: 10 | J22: 5000008679 | K22: 4.2.1 Ventilacion mecanica pecera S1 Arb | L22: 46087 | M22: JVASQUEZ | N22: ZSPC | P22: C890402550 | Q22: AIRE CARIBE S.A | R22: 308097828 | S22: =Tabla1[[#This Row],[Valor total]]/'T.C.'!$B$5 -> 83767.762 | T22: COP | U22: false
A23: 1100 | B23: =LEFT(Tabla1[[#This Row],[Organización compras]],2) -> CL | C23: CL01 | D23: 930 | E23: =VLOOKUP(Tabla1[[#This Row],[Grupo de compras]],'Grupo compras'!$A$1:$B$115,2,FALSE) -> Corp Desarro. TI | F23: KBOYE | G23: =LEFT(Tabla1[[#This Row],[Solicitud de pedido]],2) -> 12 | H23: 1200144420 | I23: 10 | J23: 4900148958 | K23: SOM: SAP BTP y API AWS | L23: 46044 | M23: KBOYE | N23: ZSRV | P23: 77050473 | Q23: STL METACONSULTING SPA | R23: 1994 | S23: =Tabla1[[#This Row],[Valor total]]/'T.C.'!$B$4 -> 83083.333 | T23: UF | U23: false
A24: 1100 | B24: =LEFT(Tabla1[[#This Row],[Organización compras]],2) -> CL | C24: CL01 | D24: 604 | E24: =VLOOKUP(Tabla1[[#This Row],[Grupo de compras]],'Grupo compras'!$A$1:$B$115,2,FALSE) -> CL Marketing Mall | F24: IIBANEZ | G24: =LEFT(Tabla1[[#This Row],[Solicitud de pedido]],2) -> 13 | H24: 1300008826 | I24: 10 | J24: 5000008555 | K24: CONTRATO STITCH | L24: 46029 | M24: IIBANEZ | N24: ZSPC | P24: 99557160 | Q24: CINECOLOR FILMS CHILE SPA. | R24: 76035000 | S24: =Tabla1[[#This Row],[Valor total]]/'T.C.'!$B$3 -> 82117.439 | T24: CLP | U24: false
A25: MIN | B25: =LEFT(Tabla1[[#This Row],[Organización compras]],2) -> PE | C25: PE01 | D25: 802 | E25: =VLOOKUP(Tabla1[[#This Row],[Grupo de compras]],'Grupo compras'!$A$1:$B$115,2,FALSE) -> PE Ops Mall | F25: cpisfil | H25: 1300008965 | I25: 10 | J25: 5000008688 | K25: Filtros para agua de pozo Minka | L25: 46092 | M25: EXT_EDAVILA | N25: ZSPC | P25: P38820311 | Q25: NCH PERU S.A | R25: 80000 | S25: =Tabla1[[#This Row],[Valor total]] -> 80000 | T25: USD | U25: false
A26: 1100 | B26: =LEFT(Tabla1[[#This Row],[Organización compras]],2) -> CL | C26: CL01 | D26: 928 | E26: =VLOOKUP(Tabla1[[#This Row],[Grupo de compras]],'Grupo compras'!$A$1:$B$115,2,FALSE) -> Corp Gest Riesgo | F26: cfuentes | G26: =LEFT(Tabla1[[#This Row],[Solicitud de pedido]],2) -> 14 | H26: 1400009185 | I26: 20 | J26: 5400006752 | K26: Endoso inclusión Mall IV Subterráneos - | L26: 46044 | M26: PMUNOZ | N26: ZPMH | P26: 99288000 | Q26: SOUTHBRIDGE COMPANIA DE SEGUROS | R26: 1861.63 | S26: =Tabla1[[#This Row],[Valor total]]/'T.C.'!$B$4 -> 77567.917 | T26: UF | U26: false
A27: BOG | B27: =LEFT(Tabla1[[#This Row],[Organización compras]],2) -> CO | C27: CO01 | D27: 702 | E27: =VLOOKUP(Tabla1[[#This Row],[Grupo de compras]],'Grupo compras'!$A$1:$B$115,2,FALSE) -> CO Ops Mall | F27: CAROL CORTES | G27: =LEFT(Tabla1[[#This Row],[Solicitud de pedido]],2) -> 13 | H27: 1300008930 | I27: 10 | J27: 5000008651 | K27: PARKING GASTO ESTACIONA MARZO A DIC 2026 | L27: 46073 | M27: EXT_APAREDES | N27: ZSPC | P27: C900038616 | Q27: CBRE COLOMBIA SAS | R27: 258044630 | S27: =Tabla1[[#This Row],[Valor total]]/'T.C.'!$B$5 -> 70158.953 | T27: COP | U27: false
A28: 1100 | B28: =LEFT(Tabla1[[#This Row],[Organización compras]],2) -> CL | C28: CL01 | D28: 907 | E28: =VLOOKUP(Tabla1[[#This Row],[Grupo de compras]],'Grupo compras'!$A$1:$B$115,2,FALSE) -> Corp Desarrollo | F28: AHERRERA | H28: 1300008959 | I28: 10 | J28: 5000008687 | K28: Mall Paseo Quilín | L28: 46092 | M28: DQUINTANA | N28: ZSPC | P28: 82586835 | Q28: BROADWAY MALYAN ESPAÑA ARQUITECTOS | R28: 70000 | S28: =Tabla1[[#This Row],[Valor total]] -> 70000 | T28: USD | U28: false
A29: ACO | B29: =LEFT(Tabla1[[#This Row],[Organización compras]],2) -> CL | C29: CL01 | D29: 602 | E29: =VLOOKUP(Tabla1[[#This Row],[Grupo de compras]],'Grupo compras'!$A$1:$B$115,2,FALSE) -> CL Ops Mall | F29: FGONZALEZ | G29: =LEFT(Tabla1[[#This Row],[Solicitud de pedido]],2) -> 12 | H29: 1200145379 | I29: 10 | J29: 4900149938 | K29: Equipamiento Fortinet Backbone | L29: 46063 | M29: FGONZALEZG | N29: ZSRV | P29: 77884668 | Q29: IT MORE SPA | R29: 69264.64 | S29: =Tabla1[[#This Row],[Valor total]] -> 69264.64 | T29: USD | U29: false
A30: 1100 | B30: =LEFT(Tabla1[[#This Row],[Organización compras]],2) -> CL | C30: CL01 | D30: 622 | E30: =VLOOKUP(Tabla1[[#This Row],[Grupo de compras]],'Grupo compras'!$A$1:$B$115,2,FALSE) -> CL Arq Mall | F30: P RAMIREZ | G30: =LEFT(Tabla1[[#This Row],[Solicitud de pedido]],2) -> 13 | H30: 1300008885 | I30: 10 | J30: 5000008633 | K30: SERV INSP TECNICA LOCALES PAK 2026 | L30: 46059 | M30: BILLESCA | N30: ZSPC | P30: 76088833 | Q30: ASESORIAS E INVERSIONES FAUNDEZ LAT | R30: 1640 | S30: =Tabla1[[#This Row],[Valor total]]/'T.C.'!$B$4 -> 68333.333 | T30: UF | U30: false
A31: 1100 | B31: =LEFT(Tabla1[[#This Row],[Organización compras]],2) -> CL | C31: CL01 | D31: 914 | E31: =VLOOKUP(Tabla1[[#This Row],[Grupo de compras]],'Grupo compras'!$A$1:$B$115,2,FALSE) -> Corp Explo. TI | F31: ACARVAJAL | G31: =LEFT(Tabla1[[#This Row],[Solicitud de pedido]],2) -> 12 | H31: 1200144090 | I31: 10 | J31: 4900148892 | K31: Globant Salesforce Core 2026 | L31: 46037 | M31: ACARVAJAL | N31: ZSRV | O31: SER_GRAL | P31: 76411210 | Q31: SISTEMAS GLOBALES CHILE-ASESORIAS | R31: 1608 | S31: =Tabla1[[#This Row],[Valor total]]/'T.C.'!$B$4 -> 67000 | T31: UF | U31: false
A32: 3100 | B32: =LEFT(Tabla1[[#This Row],[Organización compras]],2) -> PE | C32: PE01 | D32: 808 | E32: =VLOOKUP(Tabla1[[#This Row],[Grupo de compras]],'Grupo compras'!$A$1:$B$115,2,FALSE) -> PE Área Legal | F32: GOLIVERI | G32: =LEFT(Tabla1[[#This Row],[Solicitud de pedido]],2) -> 12 | H32: 1200145069 | I32: 10 | J32: 4900149771 | K32: Dieta Director Periodo - Ene a Dic 2026 | L32: 46058 | M32: SGARIBAY | N32: ZSRV | P32: P07276734 | Q32: CESAR EMILIO RODRIGUEZ LARRAIN SALI | R32: 65217.39 | S32: =Tabla1[[#This Row],[Valor total]] -> 65217.39 | T32: USD | U32: false
A33: 1100 | B33: =LEFT(Tabla1[[#This Row],[Organización compras]],2) -> CL | C33: CL01 | D33: 928 | E33: =VLOOKUP(Tabla1[[#This Row],[Grupo de compras]],'Grupo compras'!$A$1:$B$115,2,FALSE) -> Corp Gest Riesgo | F33: cfuentes | H33: 1400009354 | I33: 10 | J33: 5400006845 | K33: Endoso prórroga Responsabilidad Civil Ma | L33: 46094 | M33: PMUNOZ | N33: ZPMH | P33: 99225000 | Q33: CHUBB SEGUROS CHILE S.A. | R33: 1478.08 | S33: =Tabla1[[#This Row],[Valor total]]/'T.C.'!$B$4 -> 61586.667 | T33: UF | U33: false
A34: 2400 | B34: =LEFT(Tabla1[[#This Row],[Organización compras]],2) -> CL | C34: CL01 | D34: 602 | E34: =VLOOKUP(Tabla1[[#This Row],[Grupo de compras]],'Grupo compras'!$A$1:$B$115,2,FALSE) -> CL Ops Mall | F34: R.Mesa | G34: =LEFT(Tabla1[[#This Row],[Solicitud de pedido]],2) -> 13 | H34: 1300008907 | I34: 10 | J34: 5000008653 | K34: SERVICIO CCTV 2026 | L34: 46072 | M34: MPINO | N34: ZSPC | P34: 99512120 | Q34: SECURITAS S.A | R34: 55887312 | S34: =Tabla1[[#This Row],[Valor total]]/'T.C.'!$B$3 -> 60358.031 | T34: CLP | U34: false
A35: 2400 | B35: =LEFT(Tabla1[[#This Row],[Organización compras]],2) -> CL | C35: CL01 | D35: 602 | E35: =VLOOKUP(Tabla1[[#This Row],[Grupo de compras]],'Grupo compras'!$A$1:$B$115,2,FALSE) -> CL Ops Mall | F35: RMESA | G35: =LEFT(Tabla1[[#This Row],[Solicitud de pedido]],2) -> 12 | H35: 1200145555 | I35: 10 | J35: 4900150043 | K35: Impermeabilización sector zocalo | L35: 46066 | M35: PCAMPOS | N35: ZSRV | P35: 76694376 | Q35: SERVICIOS INDUSTRIALES ELMEC LIMITA | R35: 52421617 | S35: =Tabla1[[#This Row],[Valor total]]/'T.C.'!$B$3 -> 56615.097 | T35: CLP | U35: false
A36: 1100 | B36: =LEFT(Tabla1[[#This Row],[Organización compras]],2) -> CL | C36: CL01 | D36: 602 | E36: =VLOOKUP(Tabla1[[#This Row],[Grupo de compras]],'Grupo compras'!$A$1:$B$115,2,FALSE) -> CL Ops Mall | F36: JFlores | G36: =LEFT(Tabla1[[#This Row],[Solicitud de pedido]],2) -> 13 | H36: 1300008929 | I36: 10 | J36: 5000008671 | K36: SP Kowski Delivery Sept- Dic 2026 | L36: 46085 | M36: JFLORES | N36: ZSPC | P36: 78232224 | Q36: SERVICIOS IKOW SPA | R36: 51000000 | S36: =Tabla1[[#This Row],[Valor total]]/'T.C.'!$B$3 -> 55079.758 | T36: CLP | U36: false
A37: MIN | B37: =LEFT(Tabla1[[#This Row],[Organización compras]],2) -> PE | C37: PE01 | D37: 802 | E37: =VLOOKUP(Tabla1[[#This Row],[Grupo de compras]],'Grupo compras'!$A$1:$B$115,2,FALSE) -> PE Ops Mall | F37: cpisfil | G37: =LEFT(Tabla1[[#This Row],[Solicitud de pedido]],2) -> 13 | H37: 1300008849 | I37: 10 | J37: 5000008588 | K37: serv op PTAR RM ene-dic 26 | L37: 46044 | M37: EXT_EDAVILA | N37: ZSPC | P37: P60384983 | Q37: FLOWEN S.A.C | R37: 186733.68 | S37: =Tabla1[[#This Row],[Valor total]]/'T.C.'!$B$2 -> 54125.704 | T37: PEN | U37: false
A38: MAM | B38: =LEFT(Tabla1[[#This Row],[Organización compras]],2) -> CL | C38: CL01 | D38: 634 | E38: =VLOOKUP(Tabla1[[#This Row],[Grupo de compras]],'Grupo compras'!$A$1:$B$115,2,FALSE) -> CL Proyectos 5 | F38: RSOUPER | G38: =LEFT(Tabla1[[#This Row],[Solicitud de pedido]],2) -> 12 | H38: 1200143928 | I38: 10 | J38: 4900148681 | K38: ITO Desmantelamiento Corona MAM | L38: 46035 | M38: EXT_AYEPEZ | N38: ZSRV | P38: 76088833 | Q38: ASESORIAS E INVERSIONES FAUNDEZ LAT | R38: 1246 | S38: =Tabla1[[#This Row],[Valor total]]/'T.C.'!$B$4 -> 51916.667 | T38: UF | U38: false
A39: 6000 | B39: =LEFT(Tabla1[[#This Row],[Organización compras]],2) -> PE | C39: PEMP | D39: 802 | E39: =VLOOKUP(Tabla1[[#This Row],[Grupo de compras]],'Grupo compras'!$A$1:$B$115,2,FALSE) -> PE Ops Mall | F39: KALVAN | G39: =LEFT(Tabla1[[#This Row],[Solicitud de pedido]],2) -> 12 | H39: 1200144795 | I39: 10 | J39: 4900149468 | K39: REVISIÓN_INDEPENDENCIA_ENERO_2026 | L39: 46051 | M39: EXT_KNOLASCO | N39: ZSRV | O39: SER_MANTO | P39: P49259204 | Q39: AF CONCEPT S.A.C. | R39: 178800 | S39: =Tabla1[[#This Row],[Valor total]]/'T.C.'!$B$2 -> 51826.087 | T39: PEN | U39: false
A40: 1100 | B40: =LEFT(Tabla1[[#This Row],[Organización compras]],2) -> CL | C40: CL01 | D40: 915 | E40: =VLOOKUP(Tabla1[[#This Row],[Grupo de compras]],'Grupo compras'!$A$1:$B$115,2,FALSE) -> Corp Des Digital | F40: N Gallardo | H40: 1300008973 | I40: 10 | J40: 5000008699 | K40: Equipo desarrollo P Locatario Q1 2026 | L40: 46099 | M40: NGALLARDO | N40: ZSPC | P40: 76516485 | Q40: APIUX TECNOLOGIA SPA | R40: 1230 | S40: =Tabla1[[#This Row],[Valor total]]/'T.C.'!$B$4 -> 51250 | T40: UF | U40: false
A41: 1100 | B41: =LEFT(Tabla1[[#This Row],[Organización compras]],2) -> CL | C41: CL01 | D41: 910 | E41: =VLOOKUP(Tabla1[[#This Row],[Grupo de compras]],'Grupo compras'!$A$1:$B$115,2,FALSE) -> Corp A. Personas | F41: CCHUECAS | G41: =LEFT(Tabla1[[#This Row],[Solicitud de pedido]],2) -> 14 | H41: 1400009134 | I41: 10 | J41: 5400006728 | K41: Prestación de Servicio dic´25 | L41: 46035 | M41: DQUINTANA | N41: ZPMH | P41: 15747176 | Q41: JULIO MUÑOZ HERRERA | R41: 46991069 | S41: =Tabla1[[#This Row],[Valor total]]/'T.C.'!$B$3 -> 50750.131 | T41: CLP | U41: false
A42: 1100 | B42: =LEFT(Tabla1[[#This Row],[Organización compras]],2) -> CL | C42: CL01 | D42: 613 | E42: =VLOOKUP(Tabla1[[#This Row],[Grupo de compras]],'Grupo compras'!$A$1:$B$115,2,FALSE) -> CL Gcia Ops | F42: p.herrera | G42: =LEFT(Tabla1[[#This Row],[Solicitud de pedido]],2) -> 12 | H42: 1200144813 | I42: 10 | J42: 4900149430 | K42: EXTRACCIÓN DE DATOS SSBB 2026 | L42: 46051 | M42: EXT_PHERRERA | N42: ZSRV | P42: 76229358 | Q42: INGENIERIA Y ENERGIA NEGAWATT LIMIT | R42: 1200 | S42: =Tabla1[[#This Row],[Valor total]]/'T.C.'!$B$4 -> 50000 | T42: UF | U42: false
A43: 1100 | B43: =LEFT(Tabla1[[#This Row],[Organización compras]],2) -> CL | C43: CL01 | D43: 602 | E43: =VLOOKUP(Tabla1[[#This Row],[Grupo de compras]],'Grupo compras'!$A$1:$B$115,2,FALSE) -> CL Ops Mall | F43: p.herrera | H43: 1200147097 | I43: 10 | J43: 4900151291 | K43: Registro lecturas app | L43: 46092 | M43: EXT_PHERRERA | N43: ZSRV | P43: 76061803 | Q43: RIBE ASESORIAS Y SERVICIOS DE INGEN | R43: 1200 | S43: =Tabla1[[#This Row],[Valor total]]/'T.C.'!$B$4 -> 50000 | T43: UF | U43: false
A44: 1100 | B44: =LEFT(Tabla1[[#This Row],[Organización compras]],2) -> CL | C44: CL01 | D44: 935 | E44: =VLOOKUP(Tabla1[[#This Row],[Grupo de compras]],'Grupo compras'!$A$1:$B$115,2,FALSE) -> Corp Gte C Comerc | F44: nbarros | H44: 1200147497 | I44: 20 | J44: 4900151647 | K44: Fase 2 Dux | L44: 46098 | M44: NBARROS | N44: ZSRV | P44: 77041877 | Q44: DUX PARTNERS SPA | R44: 1158 | S44: =Tabla1[[#This Row],[Valor total]]/'T.C.'!$B$4 -> 48250 | T44: UF | U44: false
A45: 1100 | B45: =LEFT(Tabla1[[#This Row],[Organización compras]],2) -> CL | C45: CL01 | D45: 937 | E45: =VLOOKUP(Tabla1[[#This Row],[Grupo de compras]],'Grupo compras'!$A$1:$B$115,2,FALSE) -> Corp Business Int | F45: EROSALES | G45: =LEFT(Tabla1[[#This Row],[Solicitud de pedido]],2) -> 13 | H45: 1300008884 | I45: 10 | J45: 5000008626 | K45: ED APP SOHO DEV 2026 | L45: 46058 | M45: EROSALES | N45: ZSPC | P45: 99526860 | Q45: SOHO CHILE COM S A | R45: 1133 | S45: =Tabla1[[#This Row],[Valor total]]/'T.C.'!$B$4 -> 47208.333 | T45: UF | U45: false
A46: 1100 | B46: =LEFT(Tabla1[[#This Row],[Organización compras]],2) -> CL | C46: CL01 | D46: 937 | E46: =VLOOKUP(Tabla1[[#This Row],[Grupo de compras]],'Grupo compras'!$A$1:$B$115,2,FALSE) -> Corp Business Int | F46: EROSALES | G46: =LEFT(Tabla1[[#This Row],[Solicitud de pedido]],2) -> 13 | H46: 1300008887 | I46: 10 | J46: 5000008635 | K46: ED APP GLABS DEV 2026 | L46: 46059 | M46: EROSALES | N46: ZSPC | P46: 76233728 | Q46: GARAGE TECHNOLOGIES SPA | R46: 1125 | S46: =Tabla1[[#This Row],[Valor total]]/'T.C.'!$B$4 -> 46875 | T46: UF | U46: false
A47: 1100 | B47: =LEFT(Tabla1[[#This Row],[Organización compras]],2) -> CL | C47: CL01 | D47: 910 | E47: =VLOOKUP(Tabla1[[#This Row],[Grupo de compras]],'Grupo compras'!$A$1:$B$115,2,FALSE) -> Corp A. Personas | F47: CCHUECAS | G47: =LEFT(Tabla1[[#This Row],[Solicitud de pedido]],2) -> 14 | H47: 1400009134 | I47: 20 | J47: 5400006728 | K47: Prestación de Servicio ene´26 | L47: 46035 | M47: DQUINTANA | N47: ZPMH | P47: 15747176 | Q47: JULIO MUÑOZ HERRERA | R47: 43400752 | S47: =Tabla1[[#This Row],[Valor total]]/'T.C.'!$B$3 -> 46872.606 | T47: CLP | U47: false
A48: 1100 | B48: =LEFT(Tabla1[[#This Row],[Organización compras]],2) -> CL | C48: CL01 | D48: 910 | E48: =VLOOKUP(Tabla1[[#This Row],[Grupo de compras]],'Grupo compras'!$A$1:$B$115,2,FALSE) -> Corp A. Personas | F48: CCHUECAS | G48: =LEFT(Tabla1[[#This Row],[Solicitud de pedido]],2) -> 14 | H48: 1400009134 | I48: 30 | J48: 5400006728 | K48: Prestación de Servicio feb´26 | L48: 46035 | M48: DQUINTANA | N48: ZPMH | P48: 15747176 | Q48: JULIO MUÑOZ HERRERA | R48: 43400752 | S48: =Tabla1[[#This Row],[Valor total]]/'T.C.'!$B$3 -> 46872.606 | T48: CLP | U48: false
A49: BOG | B49: =LEFT(Tabla1[[#This Row],[Organización compras]],2) -> CO | C49: CO01 | D49: 702 | E49: =VLOOKUP(Tabla1[[#This Row],[Grupo de compras]],'Grupo compras'!$A$1:$B$115,2,FALSE) -> CO Ops Mall | F49: CAROL CORTES | G49: =LEFT(Tabla1[[#This Row],[Solicitud de pedido]],2) -> 12 | H49: 1200145503 | I49: 10 | J49: 4900149939 | K49: Serv logistica PMT Febrero a Dic 2026 | L49: 46065 | M49: EXT_APAREDES | N49: ZSRV | P49: C901213703 | Q49: SAFE PEOPLE SAS | R49: 170000000 | S49: =Tabla1[[#This Row],[Valor total]]/'T.C.'!$B$5 -> 46220.772 | T49: COP | U49: false
A50: 1100 | B50: =LEFT(Tabla1[[#This Row],[Organización compras]],2) -> CL | C50: CL01 | D50: 635 | E50: =VLOOKUP(Tabla1[[#This Row],[Grupo de compras]],'Grupo compras'!$A$1:$B$115,2,FALSE) -> CL Proyectos 6 | F50: CGARCIA | G50: =LEFT(Tabla1[[#This Row],[Solicitud de pedido]],2) -> 12 | H50: 1200145047 | I50: 10 | J50: 4900149641 | K50: Adicionales Remodelación Ofc Operaciones | L50: 46057 | M50: EXT_AYEPEZ | N50: ZSRV | P50: 78802550 | Q50: CONSTRUCTORA LAGO RINIHUE LIMITADA | R50: 1025.26 | S50: =Tabla1[[#This Row],[Valor total]]/'T.C.'!$B$4 -> 42719.167 | T50: UF | U50: false
A51: 1100 | B51: =LEFT(Tabla1[[#This Row],[Organización compras]],2) -> CL | C51: CL01 | D51: 928 | E51: =VLOOKUP(Tabla1[[#This Row],[Grupo de compras]],'Grupo compras'!$A$1:$B$115,2,FALSE) -> Corp Gest Riesgo | F51: cfuentes | G51: =LEFT(Tabla1[[#This Row],[Solicitud de pedido]],2) -> 14 | H51: 1400009075 | I51: 10 | J51: 5400006687 | K51: Ciberseguridad 28NOV2025-28NOV202 PArauc | L51: 46029 | M51: PMUNOZ | N51: ZPMH | P51: 99225000 | Q51: CHUBB SEGUROS CHILE S.A. | R51: 42616.21 | S51: =Tabla1[[#This Row],[Valor total]] -> 42616.21 | T51: USD | U51: false
A52: ACO | B52: =LEFT(Tabla1[[#This Row],[Organización compras]],2) -> CL | C52: CL01 | D52: 602 | E52: =VLOOKUP(Tabla1[[#This Row],[Grupo de compras]],'Grupo compras'!$A$1:$B$115,2,FALSE) -> CL Ops Mall | F52: FGONZALEZG | G52: =LEFT(Tabla1[[#This Row],[Solicitud de pedido]],2) -> 12 | H52: 1200145518 | I52: 10 | J52: 4900149970 | K52: Habilitacion estacionamiento Parking II | L52: 46065 | M52: FGONZALEZG | N52: ZSRV | P52: 77173964 | Q52: FLOREZ INGENIERIA Y CONSTRUCCION | R52: 39447935 | S52: =Tabla1[[#This Row],[Valor total]]/'T.C.'!$B$3 -> 42603.582 | T52: CLP | U52: false
A53: MAM | B53: =LEFT(Tabla1[[#This Row],[Organización compras]],2) -> CL | C53: CL01 | D53: 604 | E53: =VLOOKUP(Tabla1[[#This Row],[Grupo de compras]],'Grupo compras'!$A$1:$B$115,2,FALSE) -> CL Marketing Mall | F53: JGORICHON | G53: =LEFT(Tabla1[[#This Row],[Solicitud de pedido]],2) -> 13 | H53: 1300008815 | I53: 10 | J53: 5000008558 | K53: CONTRATO VDV STITCH | L53: 46029 | M53: JGORICHON | N53: ZSPC | P53: 99557160 | Q53: CINECOLOR FILMS CHILE SPA. | R53: 39215000 | S53: =Tabla1[[#This Row],[Valor total]]/'T.C.'!$B$3 -> 42352.014 | T53: CLP | U53: false
A54: MQU | B54: =LEFT(Tabla1[[#This Row],[Organización compras]],2) -> CL | C54: CL01 | D54: 634 | E54: =VLOOKUP(Tabla1[[#This Row],[Grupo de compras]],'Grupo compras'!$A$1:$B$115,2,FALSE) -> CL Proyectos 5 | F54: RMOYA | G54: =LEFT(Tabla1[[#This Row],[Solicitud de pedido]],2) -> 12 | H54: 1200146259 | I54: 10 | J54: 4900150564 | K54: Caracterización Arqueológica | L54: 46077 | M54: EXT_AYEPEZ | N54: ZSRV | P54: 76780604 | Q54: NATIVA GLOBAL SPA | R54: 995.7 | S54: =Tabla1[[#This Row],[Valor total]]/'T.C.'!$B$4 -> 41487.5 | T54: UF | U54: false
A55: 1100 | B55: =LEFT(Tabla1[[#This Row],[Organización compras]],2) -> CL | C55: CL01 | D55: 930 | E55: =VLOOKUP(Tabla1[[#This Row],[Grupo de compras]],'Grupo compras'!$A$1:$B$115,2,FALSE) -> Corp Desarro. TI | F55: FMANRIQUEZ | G55: =LEFT(Tabla1[[#This Row],[Solicitud de pedido]],2) -> 12 | H55: 1200145875 | I55: 10 | J55: 4900150165 | K55: Harmony - Protección phishing y malware | L55: 46071 | M55: FMANRIQUEZ | N55: ZSRV | P55: 96768440 | Q55: NOVARED CHILE S.A | R55: 41293.76 | S55: =Tabla1[[#This Row],[Valor total]] -> 41293.76 | T55: USD | U55: false
A56: 1100 | B56: =LEFT(Tabla1[[#This Row],[Organización compras]],2) -> CL | C56: CL01 | D56: 935 | E56: =VLOOKUP(Tabla1[[#This Row],[Grupo de compras]],'Grupo compras'!$A$1:$B$115,2,FALSE) -> Corp Gte C Comerc | F56: nbarros | H56: 1200147497 | I56: 10 | J56: 4900151647 | K56: Fase 1 Dux | L56: 46098 | M56: NBARROS | N56: ZSRV | P56: 77041877 | Q56: DUX PARTNERS SPA | R56: 964 | S56: =Tabla1[[#This Row],[Valor total]]/'T.C.'!$B$4 -> 40166.667 | T56: UF | U56: false
A57: PAG | B57: =LEFT(Tabla1[[#This Row],[Organización compras]],2) -> CO | C57: CO01 | D57: 711 | E57: =VLOOKUP(Tabla1[[#This Row],[Grupo de compras]],'Grupo compras'!$A$1:$B$115,2,FALSE) -> CO A.Finanzas | F57: AALCOCER | G57: =LEFT(Tabla1[[#This Row],[Solicitud de pedido]],2) -> 12 | H57: 1200144304 | I57: 10 | J57: 4900148920 | K57: EXPENSAS ENE - DIC26 LOCAL B Y C PH ALE | L57: 46042 | M57: EXT_VGONZALE | N57: ZSRV | P57: C901842487 | Q57: PARQUE ALEGRA CENTRO | R57: 145381524 | S57: =Tabla1[[#This Row],[Valor total]]/'T.C.'!$B$5 -> 39527.331 | T57: COP | U57: false
A58: 1100 | B58: =LEFT(Tabla1[[#This Row],[Organización compras]],2) -> CL | C58: CL01 | D58: 626 | E58: =VLOOKUP(Tabla1[[#This Row],[Grupo de compras]],'Grupo compras'!$A$1:$B$115,2,FALSE) -> CL Proyectos 3 | F58: DGONZALEZ | G58: =LEFT(Tabla1[[#This Row],[Solicitud de pedido]],2) -> 12 | H58: 1200144367 | I58: 10 | J58: 4900149014 | K58: Extensión ITO - Otras Obras Alejandro Pa | L58: 46043 | M58: EXT_AYEPEZ | N58: ZSRV | P58: 79906490 | Q58: WSP CHILE S.A | R58: 948 | S58: =Tabla1[[#This Row],[Valor total]]/'T.C.'!$B$4 -> 39500 | T58: UF | U58: false
A59: MIN | B59: =LEFT(Tabla1[[#This Row],[Organización compras]],2) -> PE | C59: PE01 | D59: 802 | E59: =VLOOKUP(Tabla1[[#This Row],[Grupo de compras]],'Grupo compras'!$A$1:$B$115,2,FALSE) -> PE Ops Mall | F59: CPISFIL | G59: =LEFT(Tabla1[[#This Row],[Solicitud de pedido]],2) -> 13 | H59: 1300008813 | I59: 10 | J59: 5000008552 | K59: Serv mensual de recojo de residuos-nov25 | L59: 46027 | M59: EXT_EDAVILA | N59: ZSPC | P59: P60839151 | Q59: ECOLOGIA SERVICIOS Y TRANSPORTE S.A | R59: 134400 | S59: =Tabla1[[#This Row],[Valor total]]/'T.C.'!$B$2 -> 38956.522 | T59: PEN | U59: false
A60: 2200 | B60: =LEFT(Tabla1[[#This Row],[Organización compras]],2) -> CL | C60: CL01 | D60: 602 | E60: =VLOOKUP(Tabla1[[#This Row],[Grupo de compras]],'Grupo compras'!$A$1:$B$115,2,FALSE) -> CL Ops Mall | F60: FQUEZADA | G60: =LEFT(Tabla1[[#This Row],[Solicitud de pedido]],2) -> 12 | H60: 1200146580 | I60: 10 | J60: 4900151025 | K60: CAPEX IMPERMEBILIZADION CUBIERTA | L60: 46084 | M60: FQUEZADA | N60: ZSRV | P60: 77199936 | Q60: DESTRAKUB CONSTRUCTORA LIMITADA | R60: 34913129 | S60: =Tabla1[[#This Row],[Valor total]]/'T.C.'!$B$3 -> 37706.013 | T60: CLP | U60: false
A61: 1100 | B61: =LEFT(Tabla1[[#This Row],[Organización compras]],2) -> CL | C61: CL01 | D61: 912 | E61: =VLOOKUP(Tabla1[[#This Row],[Grupo de compras]],'Grupo compras'!$A$1:$B$115,2,FALSE) -> Corp Gcia Finanza | F61: vbirrell | G61: =LEFT(Tabla1[[#This Row],[Solicitud de pedido]],2) -> 13 | H61: 1300008851 | I61: 10 | J61: 5000008595 | K61: Memoria 2025 | L61: 46048 | M61: DQUINTANA | N61: ZSPC | P61: 81513400 | Q61: PRICEWATERHOUSECOOPERS | R61: 900 | S61: =Tabla1[[#This Row],[Valor total]]/'T.C.'!$B$4 -> 37500 | T61: UF | U61: false
A62: 6030 | B62: =LEFT(Tabla1[[#This Row],[Organización compras]],2) -> PE | C62: PEMP | D62: 802 | E62: =VLOOKUP(Tabla1[[#This Row],[Grupo de compras]],'Grupo compras'!$A$1:$B$115,2,FALSE) -> PE Ops Mall | F62: LHUAMAN | G62: =LEFT(Tabla1[[#This Row],[Solicitud de pedido]],2) -> 12 | H62: 1200145023 | I62: 10 | J62: 4900149482 | K62: Sum e instal termotecho cinerama | L62: 46056 | M62: LHUAMAN | N62: ZSRV | P62: P48194095 | Q62: EDIFICANDO EIRL | R62: 128761.5 | S62: =Tabla1[[#This Row],[Valor total]]/'T.C.'!$B$2 -> 37322.174 | T62: PEN | U62: false
A63: 1100 | B63: =LEFT(Tabla1[[#This Row],[Organización compras]],2) -> CL | C63: CL01 | D63: 937 | E63: =VLOOKUP(Tabla1[[#This Row],[Grupo de compras]],'Grupo compras'!$A$1:$B$115,2,FALSE) -> Corp Business Int | F63: EROSALES | G63: =LEFT(Tabla1[[#This Row],[Solicitud de pedido]],2) -> 13 | H63: 1300008884 | I63: 20 | J63: 5000008626 | K63: ED TLSS SOHO DEV 2026 | L63: 46059 | M63: EROSALES | N63: ZSPC | P63: 99526860 | Q63: SOHO CHILE COM S A | R63: 864 | S63: =Tabla1[[#This Row],[Valor total]]/'T.C.'!$B$4 -> 36000 | T63: UF | U63: false
A64: MIN | B64: =LEFT(Tabla1[[#This Row],[Organización compras]],2) -> PE | C64: PE01 | D64: 904 | E64: =VLOOKUP(Tabla1[[#This Row],[Grupo de compras]],'Grupo compras'!$A$1:$B$115,2,FALSE) -> Corp Gcia Contabi | F64: AFLORES | G64: =LEFT(Tabla1[[#This Row],[Solicitud de pedido]],2) -> 14 | H64: 1400009179 | I64: 10 | J64: 5400006760 | K64: Adicional auditoría por revisión de Mult | L64: 46051 | M64: DQUINTANA | N64: ZPMH | P64: P50464598 | Q64: TANAKA, VALDIVIA, ARRIBAS & ASOCIAD | R64: 36000 | S64: =Tabla1[[#This Row],[Valor total]] -> 36000 | T64: USD | U64: false
A65: 3540 | B65: =LEFT(Tabla1[[#This Row],[Organización compras]],2) -> PE | C65: PE01 | D65: 813 | E65: =VLOOKUP(Tabla1[[#This Row],[Grupo de compras]],'Grupo compras'!$A$1:$B$115,2,FALSE) -> PE Gcia Ops | F65: JVEGA | G65: =LEFT(Tabla1[[#This Row],[Solicitud de pedido]],2) -> 14 | H65: 1400009310 | I65: 10 | J65: 5400006819 | K65: Servicio de auditoria IA Mar-26 | L65: 46072 | M65: PRA_ARIVERA | N65: ZPMH | O65: SER_GRAL | P65: P76457803 | Q65: FROGMI S.A | R65: 36000 | S65: =Tabla1[[#This Row],[Valor total]] -> 36000 | T65: USD | U65: false
A66: 6000 | B66: =LEFT(Tabla1[[#This Row],[Organización compras]],2) -> PE | C66: PEMP | D66: 801 | E66: =VLOOKUP(Tabla1[[#This Row],[Grupo de compras]],'Grupo compras'!$A$1:$B$115,2,FALSE) -> PE Center Manager | F66: CPACHECO | G66: =LEFT(Tabla1[[#This Row],[Solicitud de pedido]],2) -> 14 | H66: 1400009267 | I66: 10 | J66: 5400006824 | K66: Parking 2026 - MPI | L66: 46071 | M66: PRA_CPACHECO | N66: ZPMH | O66: SER_GRAL | P66: P60338169 | Q66: INVERSIONES URBANISTICAS OPERADORA | R66: 123434 | S66: =Tabla1[[#This Row],[Valor total]]/'T.C.'!$B$2 -> 35777.971 | T66: PEN | U66: false
A67: 6000 | B67: =LEFT(Tabla1[[#This Row],[Organización compras]],2) -> PE | C67: PEMP | D67: 801 | E67: =VLOOKUP(Tabla1[[#This Row],[Grupo de compras]],'Grupo compras'!$A$1:$B$115,2,FALSE) -> PE Center Manager | F67: CPACHECO | G67: =LEFT(Tabla1[[#This Row],[Solicitud de pedido]],2) -> 14 | H67: 1400009267 | I67: 20 | J67: 5400006824 | K67: Parking 2026 - MPI | L67: 46071 | M67: PRA_CPACHECO | N67: ZPMH | O67: SER_GRAL | P67: P60338169 | Q67: INVERSIONES URBANISTICAS OPERADORA | R67: 123434 | S67: =Tabla1[[#This Row],[Valor total]]/'T.C.'!$B$2 -> 35777.971 | T67: PEN | U67: false
A68: 6000 | B68: =LEFT(Tabla1[[#This Row],[Organización compras]],2) -> PE | C68: PEMP | D68: 801 | E68: =VLOOKUP(Tabla1[[#This Row],[Grupo de compras]],'Grupo compras'!$A$1:$B$115,2,FALSE) -> PE Center Manager | F68: CPACHECO | G68: =LEFT(Tabla1[[#This Row],[Solicitud de pedido]],2) -> 14 | H68: 1400009267 | I68: 30 | J68: 5400006824 | K68: Parking 2026 - MPI | L68: 46071 | M68: PRA_CPACHECO | N68: ZPMH | O68: SER_GRAL | P68: P60338169 | Q68: INVERSIONES URBANISTICAS OPERADORA | R68: 123434 | S68: =Tabla1[[#This Row],[Valor total]]/'T.C.'!$B$2 -> 35777.971 | T68: PEN | U68: false
A69: 6000 | B69: =LEFT(Tabla1[[#This Row],[Organización compras]],2) -> PE | C69: PEMP | D69: 801 | E69: =VLOOKUP(Tabla1[[#This Row],[Grupo de compras]],'Grupo compras'!$A$1:$B$115,2,FALSE) -> PE Center Manager | F69: CPACHECO | G69: =LEFT(Tabla1[[#This Row],[Solicitud de pedido]],2) -> 14 | H69: 1400009267 | I69: 40 | J69: 5400006824 | K69: Parking 2026 - MPI | L69: 46071 | M69: PRA_CPACHECO | N69: ZPMH | O69: SER_GRAL | P69: P60338169 | Q69: INVERSIONES URBANISTICAS OPERADORA | R69: 123434 | S69: =Tabla1[[#This Row],[Valor total]]/'T.C.'!$B$2 -> 35777.971 | T69: PEN | U69: false
A70: 6000 | B70: =LEFT(Tabla1[[#This Row],[Organización compras]],2) -> PE | C70: PEMP | D70: 801 | E70: =VLOOKUP(Tabla1[[#This Row],[Grupo de compras]],'Grupo compras'!$A$1:$B$115,2,FALSE) -> PE Center Manager | F70: CPACHECO | G70: =LEFT(Tabla1[[#This Row],[Solicitud de pedido]],2) -> 14 | H70: 1400009267 | I70: 50 | J70: 5400006824 | K70: Parking 2026 - MPI | L70: 46071 | M70: PRA_CPACHECO | N70: ZPMH | O70: SER_GRAL | P70: P60338169 | Q70: INVERSIONES URBANISTICAS OPERADORA | R70: 123434 | S70: =Tabla1[[#This Row],[Valor total]]/'T.C.'!$B$2 -> 35777.971 | T70: PEN | U70: false
A71: 6000 | B71: =LEFT(Tabla1[[#This Row],[Organización compras]],2) -> PE | C71: PEMP | D71: 801 | E71: =VLOOKUP(Tabla1[[#This Row],[Grupo de compras]],'Grupo compras'!$A$1:$B$115,2,FALSE) -> PE Center Manager | F71: CPACHECO | G71: =LEFT(Tabla1[[#This Row],[Solicitud de pedido]],2) -> 14 | H71: 1400009267 | I71: 60 | J71: 5400006824 | K71: Parking 2026 - MPI | L71: 46071 | M71: PRA_CPACHECO | N71: ZPMH | O71: SER_GRAL | P71: P60338169 | Q71: INVERSIONES URBANISTICAS OPERADORA | R71: 123434 | S71: =Tabla1[[#This Row],[Valor total]]/'T.C.'!$B$2 -> 35777.971 | T71: PEN | U71: false
A72: 6000 | B72: =LEFT(Tabla1[[#This Row],[Organización compras]],2) -> PE | C72: PEMP | D72: 801 | E72: =VLOOKUP(Tabla1[[#This Row],[Grupo de compras]],'Grupo compras'!$A$1:$B$115,2,FALSE) -> PE Center Manager | F72: CPACHECO | G72: =LEFT(Tabla1[[#This Row],[Solicitud de pedido]],2) -> 14 | H72: 1400009267 | I72: 70 | J72: 5400006824 | K72: Parking 2026 - MPI | L72: 46071 | M72: PRA_CPACHECO | N72: ZPMH | O72: SER_GRAL | P72: P60338169 | Q72: INVERSIONES URBANISTICAS OPERADORA | R72: 123434 | S72: =Tabla1[[#This Row],[Valor total]]/'T.C.'!$B$2 -> 35777.971 | T72: PEN | U72: false
A73: 6000 | B73: =LEFT(Tabla1[[#This Row],[Organización compras]],2) -> PE | C73: PEMP | D73: 801 | E73: =VLOOKUP(Tabla1[[#This Row],[Grupo de compras]],'Grupo compras'!$A$1:$B$115,2,FALSE) -> PE Center Manager | F73: CPACHECO | G73: =LEFT(Tabla1[[#This Row],[Solicitud de pedido]],2) -> 14 | H73: 1400009267 | I73: 80 | J73: 5400006824 | K73: Parking 2026 - MPI | L73: 46071 | M73: PRA_CPACHECO | N73: ZPMH | O73: SER_GRAL | P73: P60338169 | Q73: INVERSIONES URBANISTICAS OPERADORA | R73: 123434 | S73: =Tabla1[[#This Row],[Valor total]]/'T.C.'!$B$2 -> 35777.971 | T73: PEN | U73: false
A74: 6000 | B74: =LEFT(Tabla1[[#This Row],[Organización compras]],2) -> PE | C74: PEMP | D74: 801 | E74: =VLOOKUP(Tabla1[[#This Row],[Grupo de compras]],'Grupo compras'!$A$1:$B$115,2,FALSE) -> PE Center Manager | F74: CPACHECO | G74: =LEFT(Tabla1[[#This Row],[Solicitud de pedido]],2) -> 14 | H74: 1400009267 | I74: 90 | J74: 5400006824 | K74: Parking 2026 - MPI | L74: 46071 | M74: PRA_CPACHECO | N74: ZPMH | O74: SER_GRAL | P74: P60338169 | Q74: INVERSIONES URBANISTICAS OPERADORA | R74: 123434 | S74: =Tabla1[[#This Row],[Valor total]]/'T.C.'!$B$2 -> 35777.971 | T74: PEN | U74: false
A75: 6000 | B75: =LEFT(Tabla1[[#This Row],[Organización compras]],2) -> PE | C75: PEMP | D75: 801 | E75: =VLOOKUP(Tabla1[[#This Row],[Grupo de compras]],'Grupo compras'!$A$1:$B$115,2,FALSE) -> PE Center Manager | F75: CPACHECO | G75: =LEFT(Tabla1[[#This Row],[Solicitud de pedido]],2) -> 14 | H75: 1400009267 | I75: 100 | J75: 5400006824 | K75: Parking 2026 - MPI | L75: 46071 | M75: PRA_CPACHECO | N75: ZPMH | O75: SER_GRAL | P75: P60338169 | Q75: INVERSIONES URBANISTICAS OPERADORA | R75: 123434 | S75: =Tabla1[[#This Row],[Valor total]]/'T.C.'!$B$2 -> 35777.971 | T75: PEN | U75: false
A76: 6000 | B76: =LEFT(Tabla1[[#This Row],[Organización compras]],2) -> PE | C76: PEMP | D76: 801 | E76: =VLOOKUP(Tabla1[[#This Row],[Grupo de compras]],'Grupo compras'!$A$1:$B$115,2,FALSE) -> PE Center Manager | F76: CPACHECO | G76: =LEFT(Tabla1[[#This Row],[Solicitud de pedido]],2) -> 14 | H76: 1400009267 | I76: 110 | J76: 5400006824 | K76: Parking 2026 - MPI | L76: 46071 | M76: PRA_CPACHECO | N76: ZPMH | O76: SER_GRAL | P76: P60338169 | Q76: INVERSIONES URBANISTICAS OPERADORA | R76: 123434 | S76: =Tabla1[[#This Row],[Valor total]]/'T.C.'!$B$2 -> 35777.971 | T76: PEN | U76: false
A77: PCA | B77: =LEFT(Tabla1[[#This Row],[Organización compras]],2) -> CO | C77: CO01 | D77: 702 | E77: =VLOOKUP(Tabla1[[#This Row],[Grupo de compras]],'Grupo compras'!$A$1:$B$115,2,FALSE) -> CO Ops Mall | F77: DLOZADA | G77: =LEFT(Tabla1[[#This Row],[Solicitud de pedido]],2) -> 12 | H77: 1200146144 | I77: 10 | J77: 4900150548 | K77: F4 OVERHAUL TTVV PCA 2026 | L77: 46076 | M77: EXT_AFLOREZ | N77: ZSRV | P77: C860025639 | Q77: MITSUBISHI ELECTRIC DE COLOMBIA LIM | R77: 130306313 | S77: =Tabla1[[#This Row],[Valor total]]/'T.C.'!$B$5 -> 35428.579 | T77: COP | U77: false
A78: 1100 | B78: =LEFT(Tabla1[[#This Row],[Organización compras]],2) -> CL | C78: CL01 | D78: 937 | E78: =VLOOKUP(Tabla1[[#This Row],[Grupo de compras]],'Grupo compras'!$A$1:$B$115,2,FALSE) -> Corp Business Int | F78: EROSALES | G78: =LEFT(Tabla1[[#This Row],[Solicitud de pedido]],2) -> 13 | H78: 1300008893 | I78: 10 | J78: 5000008636 | K78: ED TLSS APIUX DEV 2026 | L78: 46059 | M78: EROSALES | N78: ZSPC | P78: 76516485 | Q78: APIUX TECNOLOGIA SPA | R78: 840 | S78: =Tabla1[[#This Row],[Valor total]]/'T.C.'!$B$4 -> 35000 | T78: UF | U78: false
A79: 1100 | B79: =LEFT(Tabla1[[#This Row],[Organización compras]],2) -> CL | C79: CL01 | D79: 602 | E79: =VLOOKUP(Tabla1[[#This Row],[Grupo de compras]],'Grupo compras'!$A$1:$B$115,2,FALSE) -> CL Ops Mall | F79: fgonzalezv | G79: =LEFT(Tabla1[[#This Row],[Solicitud de pedido]],2) -> 12 | H79: 1200146337 | I79: 10 | J79: 4900150686 | K79: LPR PAO Ticketless | L79: 46078 | M79: FGONZALEZV | N79: ZSRV | P79: 76062618 | Q79: SKIDATA CHILE SPA | R79: 29548 | S79: =Tabla1[[#This Row],[Valor total]]/'T.C.'!$B$6 -> 33963.218 | T79: EUR | U79: false
A80: 1100 | B80: =LEFT(Tabla1[[#This Row],[Organización compras]],2) -> CL | C80: CL01 | D80: 910 | E80: =VLOOKUP(Tabla1[[#This Row],[Grupo de compras]],'Grupo compras'!$A$1:$B$115,2,FALSE) -> Corp A. Personas | F80: CCHUECAS | G80: =LEFT(Tabla1[[#This Row],[Solicitud de pedido]],2) -> 14 | H80: 1400009183 | I80: 10 | J80: 5400006750 | K80: Prestación de Servicio dic´25 | L80: 46043 | M80: DQUINTANA | N80: ZPMH | P80: 15643175 | Q80: PABLO ANDRES MENCHACA FERNANDEZ | R80: 31386431 | S80: =Tabla1[[#This Row],[Valor total]]/'T.C.'!$B$3 -> 33897.196 | T80: CLP | U80: false
A81: 1100 | B81: =LEFT(Tabla1[[#This Row],[Organización compras]],2) -> CL | C81: CL01 | D81: 626 | E81: =VLOOKUP(Tabla1[[#This Row],[Grupo de compras]],'Grupo compras'!$A$1:$B$115,2,FALSE) -> CL Proyectos 3 | F81: ELLA | G81: =LEFT(Tabla1[[#This Row],[Solicitud de pedido]],2) -> 12 | H81: 1200144626 | I81: 10 | J81: 4900149313 | K81: Grupo 1 Adicionales Multifamily | L81: 46049 | M81: EXT_AYEPEZ | N81: ZSRV | P81: 76247273 | Q81: ECHEVERRIA IZQUIERDO EDIFICACIONES | R81: 810.26 | S81: =Tabla1[[#This Row],[Valor total]]/'T.C.'!$B$4 -> 33760.833 | T81: UF | U81: false
A82: 1110 | B82: =LEFT(Tabla1[[#This Row],[Organización compras]],2) -> CL | C82: CL01 | D82: 634 | E82: =VLOOKUP(Tabla1[[#This Row],[Grupo de compras]],'Grupo compras'!$A$1:$B$115,2,FALSE) -> CL Proyectos 5 | F82: RSOUPER | G82: =LEFT(Tabla1[[#This Row],[Solicitud de pedido]],2) -> 12 | H82: 1200144031 | I82: 10 | J82: 4900148750 | K82: Proyectista Calculo Coquimbo | L82: 46036 | M82: EXT_AYEPEZ | N82: ZSRV | P82: 76279296 | Q82: ARANEDA INGENIEROS CONSULTORES SPA. | R82: 791 | S82: =Tabla1[[#This Row],[Valor total]]/'T.C.'!$B$4 -> 32958.333 | T82: UF | U82: false
A83: 4300 | B83: =LEFT(Tabla1[[#This Row],[Organización compras]],2) -> CO | C83: CO01 | D83: 702 | E83: =VLOOKUP(Tabla1[[#This Row],[Grupo de compras]],'Grupo compras'!$A$1:$B$115,2,FALSE) -> CO Ops Mall | F83: ARICO | G83: =LEFT(Tabla1[[#This Row],[Solicitud de pedido]],2) -> 13 | H83: 1300008888 | I83: 10 | J83: 5000008637 | K83: PARKING GASTOS ESTACIONAMIENTO FEB - DIC | L83: 46062 | M83: EXT_JTRUJILL | N83: ZSPC | P83: C900038616 | Q83: CBRE COLOMBIA SAS | R83: 118804587 | S83: =Tabla1[[#This Row],[Valor total]]/'T.C.'!$B$5 -> 32301.41 | T83: COP | U83: false
A84: 2400 | B84: =LEFT(Tabla1[[#This Row],[Organización compras]],2) -> CL | C84: CL01 | D84: 602 | E84: =VLOOKUP(Tabla1[[#This Row],[Grupo de compras]],'Grupo compras'!$A$1:$B$115,2,FALSE) -> CL Ops Mall | F84: RMESA | G84: =LEFT(Tabla1[[#This Row],[Solicitud de pedido]],2) -> 12 | H84: 1200145847 | I84: 10 | J84: 4900150296 | K84: Pavimento Ce1 | L84: 46071 | M84: PCAMPOS | N84: ZSRV | P84: 13271254 | Q84: DANIEL BLANCO LANDERO | R84: 29781750 | S84: =Tabla1[[#This Row],[Valor total]]/'T.C.'!$B$3 -> 32164.148 | T84: CLP | U84: false
A85: 1100 | B85: =LEFT(Tabla1[[#This Row],[Organización compras]],2) -> CL | C85: CL01 | D85: 602 | E85: =VLOOKUP(Tabla1[[#This Row],[Grupo de compras]],'Grupo compras'!$A$1:$B$115,2,FALSE) -> CL Ops Mall | F85: MANTONIETA | H85: 1200147366 | I85: 10 | J85: 4900151395 | K85: Repaciones elect e ilum. por contingenci | L85: 46097 | M85: EXT_CNARANJO | N85: ZSRV | P85: 76520413 | Q85: AVANZA ELECTRIC INGENIERIA Y MONTAJ | R85: 28758336 | S85: =Tabla1[[#This Row],[Valor total]]/'T.C.'!$B$3 -> 31058.866 | T85: CLP | U85: false
A86: BOG | B86: =LEFT(Tabla1[[#This Row],[Organización compras]],2) -> CO | C86: CO01 | D86: 702 | E86: =VLOOKUP(Tabla1[[#This Row],[Grupo de compras]],'Grupo compras'!$A$1:$B$115,2,FALSE) -> CO Ops Mall | F86: CAROL CORTES | G86: =LEFT(Tabla1[[#This Row],[Solicitud de pedido]],2) -> 13 | H86: 1300008829 | I86: 10 | J86: 5000008560 | K86: GASTOS REEMBOLSABLES ENERO A DIC 2026 | L86: 46035 | M86: EXT_APAREDES | N86: ZSPC | P86: C900271114 | Q86: EQUIPOS Y SISTEMAS DE PARKING S.A.S | R86: 114000000 | S86: =Tabla1[[#This Row],[Valor total]]/'T.C.'!$B$5 -> 30995.106 | T86: COP | U86: false
A87: 4300 | B87: =LEFT(Tabla1[[#This Row],[Organización compras]],2) -> CO | C87: CO01 | D87: 702 | E87: =VLOOKUP(Tabla1[[#This Row],[Grupo de compras]],'Grupo compras'!$A$1:$B$115,2,FALSE) -> CO Ops Mall | F87: ARICO | G87: =LEFT(Tabla1[[#This Row],[Solicitud de pedido]],2) -> 12 | H87: 1200146239 | I87: 10 | J87: 4900150600 | K87: CAPEX CAJERO ADVENTA PAR | L87: 46077 | M87: EXT_JTRUJILL | N87: ZSRV | P87: C901094828 | Q87: SOLUCIONES INTEGRALES DE MOVILIDAD, | R87: 110042143 | S87: =Tabla1[[#This Row],[Valor total]]/'T.C.'!$B$5 -> 29919.017 | T87: COP | U87: false
A88: 1100 | B88: =LEFT(Tabla1[[#This Row],[Organización compras]],2) -> CL | C88: CL01 | D88: 602 | E88: =VLOOKUP(Tabla1[[#This Row],[Grupo de compras]],'Grupo compras'!$A$1:$B$115,2,FALSE) -> CL Ops Mall | F88: MANTONIETA | G88: =LEFT(Tabla1[[#This Row],[Solicitud de pedido]],2) -> 12 | H88: 1200147013 | I88: 10 | J88: 4900151203 | K88: Retiro de cierres de locales | L88: 46091 | M88: EXT_CNARANJO | N88: ZSRV | P88: 76338784 | Q88: SOCIEDAD DE TRANSPORTES Y DESARROLL | R88: 711.91 | S88: =Tabla1[[#This Row],[Valor total]]/'T.C.'!$B$4 -> 29662.917 | T88: UF | U88: false
A89: 1100 | B89: =LEFT(Tabla1[[#This Row],[Organización compras]],2) -> CL | C89: CL01 | D89: 937 | E89: =VLOOKUP(Tabla1[[#This Row],[Grupo de compras]],'Grupo compras'!$A$1:$B$115,2,FALSE) -> Corp Business Int | F89: EROSALES | G89: =LEFT(Tabla1[[#This Row],[Solicitud de pedido]],2) -> 13 | H89: 1300008893 | I89: 20 | J89: 5000008636 | K89: ED APP APIUX DEV 2026 | L89: 46059 | M89: EROSALES | N89: ZSPC | P89: 76516485 | Q89: APIUX TECNOLOGIA SPA | R89: 707 | S89: =Tabla1[[#This Row],[Valor total]]/'T.C.'!$B$4 -> 29458.333 | T89: UF | U89: false
A90: 1100 | B90: =LEFT(Tabla1[[#This Row],[Organización compras]],2) -> CL | C90: CL01 | D90: 601 | E90: =VLOOKUP(Tabla1[[#This Row],[Grupo de compras]],'Grupo compras'!$A$1:$B$115,2,FALSE) -> CL Center Manager | F90: gmery | G90: =LEFT(Tabla1[[#This Row],[Solicitud de pedido]],2) -> 13 | H90: 1300008909 | I90: 10 | J90: 5000008654 | K90: Inspeccion estruc Lind PAO/PAP | L90: 46072 | M90: PMUNOZ | N90: ZSPC | P90: 76458432 | Q90: LIVE INFRASTRUCTURE DIAGNOSTICS SPA | R90: 702.26 | S90: =Tabla1[[#This Row],[Valor total]]/'T.C.'!$B$4 -> 29260.833 | T90: UF | U90: false
A91: 1100 | B91: =LEFT(Tabla1[[#This Row],[Organización compras]],2) -> CL | C91: CL01 | D91: 930 | E91: =VLOOKUP(Tabla1[[#This Row],[Grupo de compras]],'Grupo compras'!$A$1:$B$115,2,FALSE) -> Corp Desarro. TI | F91: KBOYE | G91: =LEFT(Tabla1[[#This Row],[Solicitud de pedido]],2) -> 12 | H91: 1200145516 | I91: 10 | J91: 4900149851 | K91: Jefe de Proyectos | L91: 46065 | M91: KBOYE | N91: ZSRV | P91: 96986170 | Q91: SEIDOR CHILE S.A. | R91: 692 | S91: =Tabla1[[#This Row],[Valor total]]/'T.C.'!$B$4 -> 28833.333 | T91: UF | U91: false
A92: CON | B92: =LEFT(Tabla1[[#This Row],[Organización compras]],2) -> CL | C92: CL01 | D92: 602 | E92: =VLOOKUP(Tabla1[[#This Row],[Grupo de compras]],'Grupo compras'!$A$1:$B$115,2,FALSE) -> CL Ops Mall | F92: JALVAREZV | G92: =LEFT(Tabla1[[#This Row],[Solicitud de pedido]],2) -> 12 | H92: 1200146693 | I92: 10 | J92: 4900150892 | K92: Cambio Materialidad fachada etapa 3 | L92: 46085 | M92: JALVAREZV | N92: ZSRV | P92: 76004468 | Q92: SALVADOR MORA OLIVERA CONSTRUCCIONE | R92: 26682200 | S92: =Tabla1[[#This Row],[Valor total]]/'T.C.'!$B$3 -> 28816.649 | T92: CLP | U92: false
A93: MIN | B93: =LEFT(Tabla1[[#This Row],[Organización compras]],2) -> PE | C93: PE01 | D93: 816 | E93: =VLOOKUP(Tabla1[[#This Row],[Grupo de compras]],'Grupo compras'!$A$1:$B$115,2,FALSE) -> PE Sgcia Infra | F93: AMARCHESINI | G93: =LEFT(Tabla1[[#This Row],[Solicitud de pedido]],2) -> 12 | H93: 1200145383 | I93: 10 | J93: 4900149796 | K93: Implementación para reubicación de Luana | L93: 46063 | M93: EXT_ACHIHUAN | N93: ZSRV | O93: SER_GRAL | P93: P60341980 | Q93: GRUPO JG SERVICIOS GENERALES S.A.C. | R93: 99414.06 | S93: =Tabla1[[#This Row],[Valor total]]/'T.C.'!$B$2 -> 28815.67 | T93: PEN | U93: false
A94: 3520 | B94: =LEFT(Tabla1[[#This Row],[Organización compras]],2) -> PE | C94: PE01 | D94: 816 | E94: =VLOOKUP(Tabla1[[#This Row],[Grupo de compras]],'Grupo compras'!$A$1:$B$115,2,FALSE) -> PE Sgcia Infra | F94: JSOLORZANO | G94: =LEFT(Tabla1[[#This Row],[Solicitud de pedido]],2) -> 12 | H94: 1200145760 | I94: 10 | J94: 4900150172 | K94: Trabajos en redes sanitarias Ica | L94: 46070 | M94: EXT_ACHIHUAN | N94: ZSRV | O94: SER_GRAL | P94: P54389795 | Q94: 4 TORRES ARQUITECTURA | R94: 99071.4 | S94: =Tabla1[[#This Row],[Valor total]]/'T.C.'!$B$2 -> 28716.348 | T94: PEN | U94: false
A95: ACO | B95: =LEFT(Tabla1[[#This Row],[Organización compras]],2) -> CL | C95: CL01 | D95: 602 | E95: =VLOOKUP(Tabla1[[#This Row],[Grupo de compras]],'Grupo compras'!$A$1:$B$115,2,FALSE) -> CL Ops Mall | F95: FGONZALEZG | G95: =LEFT(Tabla1[[#This Row],[Solicitud de pedido]],2) -> 12 | H95: 1200146601 | I95: 10 | J95: 4900150911 | K95: Mejora soportacion clima techumbre | L95: 46084 | M95: FGONZALEZG | N95: ZSRV | P95: 77173964 | Q95: FLOREZ INGENIERIA Y CONSTRUCCION | R95: 26251537 | S95: =Tabla1[[#This Row],[Valor total]]/'T.C.'!$B$3 -> 28351.535 | T95: CLP | U95: false
A96: 1100 | B96: =LEFT(Tabla1[[#This Row],[Organización compras]],2) -> CL | C96: CL01 | D96: 602 | E96: =VLOOKUP(Tabla1[[#This Row],[Grupo de compras]],'Grupo compras'!$A$1:$B$115,2,FALSE) -> CL Ops Mall | F96: JFlores | G96: =LEFT(Tabla1[[#This Row],[Solicitud de pedido]],2) -> 14 | H96: 1400009308 | I96: 10 | J96: 5400006833 | K96: OC Koski RRHH PAK | L96: 46077 | M96: JFLORES | N96: ZPMH | P96: 78232224 | Q96: SERVICIOS IKOW SPA | R96: 26163916 | S96: =Tabla1[[#This Row],[Valor total]]/'T.C.'!$B$3 -> 28256.905 | T96: CLP | U96: false
A97: 1100 | B97: =LEFT(Tabla1[[#This Row],[Organización compras]],2) -> CL | C97: CL01 | D97: 635 | E97: =VLOOKUP(Tabla1[[#This Row],[Grupo de compras]],'Grupo compras'!$A$1:$B$115,2,FALSE) -> CL Proyectos 6 | F97: CGARCIA | G97: =LEFT(Tabla1[[#This Row],[Solicitud de pedido]],2) -> 12 | H97: 1200144607 | I97: 10 | J97: 4900149163 | K97: ITO Oficina de Operaciones | L97: 46049 | M97: EXT_AYEPEZ | N97: ZSRV | P97: 76271954 | Q97: ASESORIAS PROYECTOS Y SERVICIOS DE | R97: 676.53 | S97: =Tabla1[[#This Row],[Valor total]]/'T.C.'!$B$4 -> 28188.75 | T97: UF | U97: false
A98: 1100 | B98: =LEFT(Tabla1[[#This Row],[Organización compras]],2) -> CL | C98: CL01 | D98: 602 | E98: =VLOOKUP(Tabla1[[#This Row],[Grupo de compras]],'Grupo compras'!$A$1:$B$115,2,FALSE) -> CL Ops Mall | F98: FJELDRES | G98: =LEFT(Tabla1[[#This Row],[Solicitud de pedido]],2) -> 12 | H98: 1200146786 | I98: 10 | J98: 4900151005 | K98: Proyecto control de accesos salas | L98: 46087 | M98: EXT_CNARANJO | N98: ZSRV | P98: 77816251 | Q98: LINK SOLUCIONES SPA | R98: 25711424 | S98: =Tabla1[[#This Row],[Valor total]]/'T.C.'!$B$3 -> 27768.216 | T98: CLP | U98: false
A99: 4150 | B99: =LEFT(Tabla1[[#This Row],[Organización compras]],2) -> CO | C99: CO01 | D99: 915 | E99: =VLOOKUP(Tabla1[[#This Row],[Grupo de compras]],'Grupo compras'!$A$1:$B$115,2,FALSE) -> Corp Des Digital | F99: fagonzalez | G99: =LEFT(Tabla1[[#This Row],[Solicitud de pedido]],2) -> 13 | H99: 1300008917 | I99: 10 | J99: 5000008644 | K99: Célula Operaciones COL Soho ENE-FEB-MAR | L99: 46071 | M99: FAGONZALEZ | N99: ZSPC | P99: C901366757 | Q99: SOHO UX COLOMBIA SAS | R99: 101598657 | S99: =Tabla1[[#This Row],[Valor total]]/'T.C.'!$B$5 -> 27623.343 | T99: COP | U99: false
A100: 2160 | B100: =LEFT(Tabla1[[#This Row],[Organización compras]],2) -> CL | C100: CL01 | D100: 602 | E100: =VLOOKUP(Tabla1[[#This Row],[Grupo de compras]],'Grupo compras'!$A$1:$B$115,2,FALSE) -> CL Ops Mall | F100: RCORTES | G100: =LEFT(Tabla1[[#This Row],[Solicitud de pedido]],2) -> 12 | H100: 1200146110 | I100: 10 | J100: 4900150660 | K100: CORRECTIVO MES DE FEBRERO | L100: 46076 | M100: EXT_CVENEGAS | N100: ZSRV | P100: 96811990 | Q100: LINKES CHILE S.A | R100: 24894446 | S100: =Tabla1[[#This Row],[Valor total]]/'T.C.'!$B$3 -> 26885.883 | T100: CLP | U100: false
...

Sheet Grupo compras
A1: GCp | B1: Denominación
A2: 601 | B2: CL Center Manager
A3: 602 | B3: CL Ops Mall
A4: 603 | B4: CL Ops Out/Strip
A5: 604 | B5: CL Marketing Mall
A6: 605 | B6: CL Gcia Ing & Proy
A7: 606 | B7: CL Gcia Comercial
A8: 607 | B8: CL Gcia Desarrollo
A9: 608 | B9: CL Área Legal
A10: 609 | B10: CL GciaMarketing
A11: 610 | B11: CL Área Personas
A12: 611 | B12: CL Admin y C. Gest
A13: 612 | B13: CL Serv al Cliente
... A115: 941 | B115: Corp Negocios

Sheet T.D.
B1: Organización compras | C1: (Todas)
B2: Grupo de compras | C2: (Todas) | F2: Tipo | G2: (Varios elementos)
B3: Fecha de solicitud | C3: (Todas)
F4: Grupo de compras | G4: Cuenta de Pedido
B5: OCs creadas | C5: Valor USD | D5: % Representación | F5: Total general
B6: 4900149406 | C6: 271383.33 | D6: 0.0368888
B7: 4900148645 | C7: 153992.46 | D7: 0.020932005
B8: 4900148769 | C8: 142350 | D8: 0.019349459 | J8: Etiquetas de fila | K8: Cantd. Pedido | L8: Valor USD | M8: % Representación
B9: 4900149553 | C9: 134188.72 | D9: 0.018240107 | J9: DCL | K9: 1838 | L9: 21453146 | M9: 0.74947483
B10: 4900150865 | C10: 117439.13 | D10: 0.015963356 | J10: DPE | K10: 1256 | L10: 3113692.4 | M10: 0.10877818
B11: 4900150608 | C11: 110996.82 | D11: 0.01508766 | J11: PEMP | K11: 918 | L11: 2462281.7 | M11: 0.086020865
B12: 4900149369 | C12: 104166.67 | D12: 0.014159246 | J12: DCO | K12: 794 | L12: 1595118.1 | M12: 0.055726133
B13: 4900148958 | C13: 83083.333 | D13: 0.011293415 | J13: Total general | K13: 4806 | L13: 28624238 | M13: 1
B14: 4900149938 | C14: 69264.64 | D14: 0.0094150567
B15: 4900148892 | C15: 67000 | D15: 0.009107227
B16: 4900149771 | C16: 65217.39 | D16: 0.008864919
B17: 4900150043 | C17: 56615.097 | D17: 0.00769562
B18: 4900148681 | C18: 51916.667 | D18: 0.0070569682
B19: 4900149468 | C19: 51826.087 | D19: 0.0070446558
B20: 4900149430 | C20: 50000 | D20: 0.0067964381
B21: 4900149939 | C21: 46220.772 | D21: 0.0062827323
B22: 4900149641 | C22: 42719.167 | D22: 0.0058067634
B23: 4900149970 | C23: 42603.582 | D23: 0.0057910522
B24: 4900150564 | C24: 41487.5 | D24: 0.0056393445
B25: 4900150165 | C25: 41293.76 | D25: 0.0056130097
... B2677: Total general | C2677: 7356794.8 | D2677: 1

Sheet Prop. Mejora
B2: MEJORA DE CUMPLIMIENTO
M3: Propuesta de mejora:
A4: Mejora 1: Matriz de decisión obligatoria para el usuario | M4: Implementar un control preventivo en el proceso de compras para solicitudes mayores a USD 50,000, basado en una matriz estandarizada de selección de SolPed, alertas de validación y revisión previa por el área de Abastecimiento, a fin de asegurar que las compras sean gestionadas bajo la modalidad correcta según su monto, naturaleza contractual y nivel de criticidad.
A5: Proponer una matriz simple de selección de SolPed:
B6: SP 12: compras puntuales hasta cierto umbral y sin necesidad de contrato
B7: SP 13 / 14: compras de contrato o superiores a USD 50,000
B8: SP 15: procesos que por su naturaleza deben pasar por licitación o por gestión del otro equipo
A9: Esto debe quedar en una guía visual muy práctica, porque muchas veces la política existe, pero el usuario no la interpreta bien o elige lo más rápido.
A10: Beneficio
A11: Evita errores por desconocimiento y estandariza el criterio entre DCL, DCO, DPE, CORP
A13: Mejora 2: Validación automática o semiautomática por monto
A14: Propuesta | M14: Resultado esperado:
B15: Que se incorpore un flujo de aprobación obligatorio de Abastecimiento | M15: Reducir errores en la tipificación de SolPed, evitar desvíos de política, disminuir retrabajos y fortalecer la trazabilidad y el cumplimiento del proceso de compras en los distintos países y corporativo.
B16: La compra supere USD 20,000
A17: Modelo similar al de excepción de cotización

Sheet T.C.
A1: Tipo de cambio | C1: 46103
A2: PEN | B2: 3.45
A3: CLP | B3: 925.93
A4: UF | B4: 0.024
A5: COP | B5: 3678
A6: EURO | B6: 0.87

Sheet Pendientes
B3: * Establecer un tipo de cambio referencial de USD $: PEN,COP,CL,UF | H3: Al 31/03 (o al último reporte)
B4: * Verificar por tipo de compas, OC migradas, año actual, porque hay contratos migratorios y acumulativos
B5: Revisar
B6: Del total de OC al corte, cuántas superan USD 20.000
B7: 113 - OC 49* | C7: Revisar aquellas que no tienen contratos
C8: Proveedor y GC las OC 49*
B10: Elaborar una PPT con la data - Resultado del análisis
B12: Adicionar a la columna: Solicitantes
B13: Gráficos por países de cuánto USD tuvo CLP, CO, PE
